action.py
action-1.1.0b4.dist-info/DESCRIPTION.rst
action-1.1.0b4.dist-info/METADATA
action-1.1.0b4.dist-info/RECORD
action-1.1.0b4.dist-info/WHEEL
action-1.1.0b4.dist-info/metadata.json
action-1.1.0b4.dist-info/top_level.txt
